README
setup.py
django_base_model/CaseInsensitiveQuerySet.py
django_base_model/ExtendedBaseModel.py
django_base_model/ExtendedBaseModelManager.py
django_base_model/__init__.py
django_base_model.egg-info/PKG-INFO
django_base_model.egg-info/SOURCES.txt
django_base_model.egg-info/dependency_links.txt
django_base_model.egg-info/requires.txt
django_base_model.egg-info/top_level.txt
django_base_model.egg-info/zip-safe