Metadata-Version: 1.0
Name: django-base-model
Version: 0.2.2
Summary: A model from which all django models can extend. Gives some additional utility functions
Home-page: http://github.com/rogeliorv/django_base_model
Author: @rogeliorv
Author-email: rogelio@rogeliorv.com
License: MIT
Keywords: django model
Platform: UNKNOWN
